pistarlab/__init__.py
pistarlab/agent.py
pistarlab/api_schema.py
pistarlab/app_backend.py
pistarlab/common.py
pistarlab/component.py
pistarlab/config.py
pistarlab/core.py
pistarlab/data_context.py
pistarlab/databuffer.py
pistarlab/dbinit.py
pistarlab/dbmodels.py
pistarlab/entity.py
pistarlab/env_base.py
pistarlab/execution_context.py
pistarlab/filestore.py
pistarlab/launcher.py
pistarlab/meta.py
pistarlab/plugin_manager.py
pistarlab/plugin_tools.py
pistarlab/remote_conn.py
pistarlab/remote_env.py
pistarlab/services.py
pistarlab/session.py
pistarlab/session_config.py
pistarlab/session_env.py
pistarlab/storage.py
pistarlab/streamer.py
pistarlab/task.py
pistarlab/task_runner.py
pistarlab/util_funcs.py
pistarlab/agents/__init__.py
pistarlab/agents/random.py
pistarlab/envs/__init__.py
pistarlab/envs/ma_test_envs.py
pistarlab/plugins/repo.json
pistarlab/plugins/pistarlab-agents-stable-baselines/README.md
pistarlab/plugins/pistarlab-agents-stable-baselines/setup.py
pistarlab/plugins/pistarlab-agents-stable-baselines/__pycache__/setup.cpython-37.pyc
pistarlab/plugins/pistarlab-agents-stable-baselines/pistarlab_agents_stable_baselines/__init__.py
pistarlab/plugins/pistarlab-agents-stable-baselines/pistarlab_agents_stable_baselines/agent.py
pistarlab/plugins/pistarlab-agents-stable-baselines/pistarlab_agents_stable_baselines/plugin.py
pistarlab/plugins/pistarlab-agents-stable-baselines/pistarlab_agents_stable_baselines/__pycache__/__init__.cpython-37.pyc
pistarlab/plugins/pistarlab-agents-stable-baselines/pistarlab_agents_stable_baselines/__pycache__/__init__.cpython-38.pyc
pistarlab/plugins/pistarlab-agents-stable-baselines/pistarlab_agents_stable_baselines/__pycache__/agent.cpython-37.pyc
pistarlab/plugins/pistarlab-agents-stable-baselines/pistarlab_agents_stable_baselines/__pycache__/agent.cpython-38.pyc
pistarlab/plugins/pistarlab-agents-stable-baselines/pistarlab_agents_stable_baselines/__pycache__/plugin.cpython-37.pyc
pistarlab/plugins/pistarlab-agents-stable-baselines/pistarlab_agents_stable_baselines.egg-info/PKG-INFO
pistarlab/plugins/pistarlab-agents-stable-baselines/pistarlab_agents_stable_baselines.egg-info/SOURCES.txt
pistarlab/plugins/pistarlab-agents-stable-baselines/pistarlab_agents_stable_baselines.egg-info/dependency_links.txt
pistarlab/plugins/pistarlab-agents-stable-baselines/pistarlab_agents_stable_baselines.egg-info/entry_points.txt
pistarlab/plugins/pistarlab-agents-stable-baselines/pistarlab_agents_stable_baselines.egg-info/requires.txt
pistarlab/plugins/pistarlab-agents-stable-baselines/pistarlab_agents_stable_baselines.egg-info/top_level.txt
pistarlab/plugins/pistarlab-envs-gym-atari/pistarlab_envs_gym_atari.egg-info/PKG-INFO
pistarlab/plugins/pistarlab-envs-gym-atari/pistarlab_envs_gym_atari.egg-info/SOURCES.txt
pistarlab/plugins/pistarlab-envs-gym-atari/pistarlab_envs_gym_atari.egg-info/dependency_links.txt
pistarlab/plugins/pistarlab-envs-gym-atari/pistarlab_envs_gym_atari.egg-info/requires.txt
pistarlab/plugins/pistarlab-envs-gym-atari/pistarlab_envs_gym_atari.egg-info/top_level.txt
pistarlab/plugins/pistarlab-envs-gym-main/pistarlab_envs_gym_main.egg-info/PKG-INFO
pistarlab/plugins/pistarlab-envs-gym-main/pistarlab_envs_gym_main.egg-info/SOURCES.txt
pistarlab/plugins/pistarlab-envs-gym-main/pistarlab_envs_gym_main.egg-info/dependency_links.txt
pistarlab/plugins/pistarlab-envs-gym-main/pistarlab_envs_gym_main.egg-info/requires.txt
pistarlab/plugins/pistarlab-envs-gym-main/pistarlab_envs_gym_main.egg-info/top_level.txt
pistarlab/plugins/pistarlab-envs-gym-minigrid/pistarlab_envs_gym_minigrid.egg-info/PKG-INFO
pistarlab/plugins/pistarlab-envs-gym-minigrid/pistarlab_envs_gym_minigrid.egg-info/SOURCES.txt
pistarlab/plugins/pistarlab-envs-gym-minigrid/pistarlab_envs_gym_minigrid.egg-info/dependency_links.txt
pistarlab/plugins/pistarlab-envs-gym-minigrid/pistarlab_envs_gym_minigrid.egg-info/requires.txt
pistarlab/plugins/pistarlab-envs-gym-minigrid/pistarlab_envs_gym_minigrid.egg-info/top_level.txt
pistarlab/plugins/pistarlab-petting-zoo/pistarlab_petting_zoo.egg-info/PKG-INFO
pistarlab/plugins/pistarlab-petting-zoo/pistarlab_petting_zoo.egg-info/SOURCES.txt
pistarlab/plugins/pistarlab-petting-zoo/pistarlab_petting_zoo.egg-info/dependency_links.txt
pistarlab/plugins/pistarlab-petting-zoo/pistarlab_petting_zoo.egg-info/requires.txt
pistarlab/plugins/pistarlab-petting-zoo/pistarlab_petting_zoo.egg-info/top_level.txt
pistarlab/plugins/pistarlab-rllib/pistarlab_rllib.egg-info/PKG-INFO
pistarlab/plugins/pistarlab-rllib/pistarlab_rllib.egg-info/SOURCES.txt
pistarlab/plugins/pistarlab-rllib/pistarlab_rllib.egg-info/dependency_links.txt
pistarlab/plugins/pistarlab-rllib/pistarlab_rllib.egg-info/requires.txt
pistarlab/plugins/pistarlab-rllib/pistarlab_rllib.egg-info/top_level.txt
pistarlab/plugins/pistarlab-simpleland/pistarlab_simpleland.egg-info/PKG-INFO
pistarlab/plugins/pistarlab-simpleland/pistarlab_simpleland.egg-info/SOURCES.txt
pistarlab/plugins/pistarlab-simpleland/pistarlab_simpleland.egg-info/dependency_links.txt
pistarlab/plugins/pistarlab-simpleland/pistarlab_simpleland.egg-info/top_level.txt
pistarlab-0.0.1.dev1.dist-info/AUTHORS.md
pistarlab-0.0.1.dev1.dist-info/LICENSE
pistarlab-0.0.1.dev1.dist-info/METADATA
pistarlab-0.0.1.dev1.dist-info/WHEEL
pistarlab-0.0.1.dev1.dist-info/entry_points.txt
pistarlab-0.0.1.dev1.dist-info/top_level.txt
pistarlab-0.0.1.dev1.dist-info/RECORD
