Metadata-Version: 2.1
Name: pistarlab
Version: 0.0.1.dev1
Summary: A modular AI agent experimentation tool.
Home-page: https://github.com/pistarlab/pistarlab/
Author: Brandyn Kusenda
Author-email: pistar3.14@gmail.com
License: Apache-2.0
Project-URL: Documentation, https://pistarlab.readthedocs.io/
Project-URL: Changelog, https://pistarlab.readthedocs.io/en/latest/changelog.html
Project-URL: Issue Tracker, https://github.com/pistarlab/pistarlab/issues
Platform: UNKNOWN
Classifier: Topic :: Software Development
Classifier: Topic :: Games/Entertainment :: Simulation
Classifier: Topic :: Scientific/Engineering :: Artificial Intelligence
Classifier: Programming Language :: Python :: 3.7
Classifier: Programming Language :: Python :: 3.8
Requires-Python: >=3.7
Requires-Dist: Flask
Requires-Dist: Flask-Cors
Requires-Dist: Flask-GraphQl
Requires-Dist: graphene
Requires-Dist: graphene-sqlalchemy
Requires-Dist: graphene-sqlalchemy-filter
Requires-Dist: aiohttp-cors
Requires-Dist: aiortc
Requires-Dist: SQLAlchemy (<1.4,>=1.3)
Requires-Dist: shortuuid
Requires-Dist: simplejson
Requires-Dist: pyinstrument
Requires-Dist: sh
Requires-Dist: ffmpeg-python
Requires-Dist: gym
Requires-Dist: matplotlib
Requires-Dist: colorama
Requires-Dist: gputil
Requires-Dist: psutil
Requires-Dist: msgpack
Requires-Dist: msgpack-numpy
Requires-Dist: pytest
Requires-Dist: psycopg2-binary
Requires-Dist: zmq
Requires-Dist: redis
Requires-Dist: pyyaml
Requires-Dist: filelock
Requires-Dist: opencv-python
Requires-Dist: xvfbwrapper
Requires-Dist: ray
Requires-Dist: pip
Provides-Extra: all
Requires-Dist: tensorflow (==2.3.1) ; extra == 'all'
Requires-Dist: torch (==1.7.1) ; extra == 'all'
Requires-Dist: torchvision (==0.8.2) ; extra == 'all'
Requires-Dist: ray[all] (==1.2.0) ; extra == 'all'
